netbox_giftwrap/__init__.py
netbox_giftwrap/csv.j2
netbox_giftwrap/datatable_footer.j2
netbox_giftwrap/datatable_header.j2
netbox_giftwrap/html.j2
netbox_giftwrap/md.j2
netbox_giftwrap/mindmap.j2
netbox_giftwrap/mp3.j2
netbox_giftwrap/netbox_giftwrap.py
netbox_giftwrap/script.py
netbox_giftwrap-2.0.1.dist-info/entry_points.txt
netbox_giftwrap-2.0.1.dist-info/LICENSE
netbox_giftwrap-2.0.1.dist-info/WHEEL
netbox_giftwrap-2.0.1.dist-info/METADATA
netbox_giftwrap-2.0.1.dist-info/RECORD
