Metadata-Version: 2.1
Name: netbox-giftwrap
Version: 2.0.1
Summary: Transform NetBox APIs into Business Ready Documents
Author: John Capobianco
Author-email: ptcapo@gmail.com
Requires-Python: >=3.8,<4.0
Classifier: Programming Language :: Python :: 3
Classifier: Programming Language :: Python :: 3.10
Classifier: Programming Language :: Python :: 3.8
Classifier: Programming Language :: Python :: 3.9
Requires-Dist: Jinja2 (>=3.1.2,<4.0.0)
Requires-Dist: PyYAML (>=6.0,<7.0)
Requires-Dist: aiofiles (>=22.1.0,<23.0.0)
Requires-Dist: aiohttp (>=3.8.3,<4.0.0)
Requires-Dist: rich-click (>=1.3.0,<2.0.0)
